{"dependencies":[{"name":"D:\\typescript_workspace\\typescript\\2chapter2\\2-16\\tsconfig.json","includedInParent":true,"mtime":1622721660503},{"name":"D:\\typescript_workspace\\typescript\\2chapter2\\2-16\\package.json","includedInParent":true,"mtime":1622722410490},{"name":"./One","loc":{"line":6,"column":36},"parent":"D:\\typescript_workspace\\typescript\\2chapter2\\2-16\\src\\Test4.ts","resolved":"D:\\typescript_workspace\\typescript\\2chapter2\\2-16\\src\\One.ts"}],"generated":{"js":"\"use strict\";\n\nvar __importDefault = this && this.__importDefault || function (mod) {\n    return mod && mod.__esModule ? mod : { \"default\": mod };\n};\nObject.defineProperty(exports, \"__esModule\", { value: true });\nvar One_1 = __importDefault(require(\"./One\"));\nOne_1.default.set(\"abc\", 23);\nconsole.log(One_1.default.get(\"abc\"));","map":{"mappings":[{"source":"src\\Test4.ts","name":null,"original":{"line":1,"column":0},"generated":{"line":7,"column":0}},{"source":"src\\Test4.ts","name":null,"original":{"line":1,"column":0},"generated":{"line":7,"column":4}},{"source":"src\\Test4.ts","name":null,"original":{"line":1,"column":0},"generated":{"line":7,"column":12}},{"source":"src\\Test4.ts","name":null,"original":{"line":1,"column":0},"generated":{"line":7,"column":28}},{"source":"src\\Test4.ts","name":null,"original":{"line":1,"column":0},"generated":{"line":7,"column":36}},{"source":"src\\Test4.ts","name":null,"original":{"line":1,"column":0},"generated":{"line":7,"column":43}},{"source":"src\\Test4.ts","name":null,"original":{"line":1,"column":0},"generated":{"line":7,"column":44}},{"source":"src\\Test4.ts","name":null,"original":{"line":1,"column":0},"generated":{"line":7,"column":45}},{"source":"src\\Test4.ts","name":null,"original":{"line":2,"column":0},"generated":{"line":8,"column":0}},{"source":"src\\Test4.ts","name":null,"original":{"line":2,"column":0},"generated":{"line":8,"column":6}},{"source":"src\\Test4.ts","name":null,"original":{"line":2,"column":0},"generated":{"line":8,"column":13}},{"source":"src\\Test4.ts","name":null,"original":{"line":2,"column":4},"generated":{"line":8,"column":14}},{"source":"src\\Test4.ts","name":null,"original":{"line":2,"column":0},"generated":{"line":8,"column":17}},{"source":"src\\Test4.ts","name":null,"original":{"line":2,"column":8},"generated":{"line":8,"column":18}},{"source":"src\\Test4.ts","name":null,"original":{"line":2,"column":0},"generated":{"line":8,"column":23}},{"source":"src\\Test4.ts","name":null,"original":{"line":2,"column":15},"generated":{"line":8,"column":25}},{"source":"src\\Test4.ts","name":null,"original":{"line":2,"column":0},"generated":{"line":8,"column":27}},{"source":"src\\Test4.ts","name":null,"original":{"line":3,"column":0},"generated":{"line":9,"column":0}},{"source":"src\\Test4.ts","name":null,"original":{"line":3,"column":8},"generated":{"line":9,"column":8}},{"source":"src\\Test4.ts","name":null,"original":{"line":3,"column":0},"generated":{"line":9,"column":11}},{"source":"src\\Test4.ts","name":null,"original":{"line":3,"column":12},"generated":{"line":9,"column":12}},{"source":"src\\Test4.ts","name":null,"original":{"line":3,"column":12},"generated":{"line":9,"column":18}},{"source":"src\\Test4.ts","name":null,"original":{"line":3,"column":12},"generated":{"line":9,"column":25}},{"source":"src\\Test4.ts","name":null,"original":{"line":3,"column":16},"generated":{"line":9,"column":26}},{"source":"src\\Test4.ts","name":null,"original":{"line":3,"column":12},"generated":{"line":9,"column":29}},{"source":"src\\Test4.ts","name":null,"original":{"line":3,"column":20},"generated":{"line":9,"column":30}},{"source":"src\\Test4.ts","name":null,"original":{"line":3,"column":12},"generated":{"line":9,"column":35}},{"source":"src\\Test4.ts","name":null,"original":{"line":3,"column":0},"generated":{"line":9,"column":36}}],"sources":{"src\\Test4.ts":"import Two from './One'\r\nTwo.set(\"abc\", 23)\r\nconsole.log(Two.get(\"abc\"))"},"lineCount":null}},"hash":"10247154e5e228935afb14a731ea64b2","cacheData":{"env":{}},"id":6}